TamilSandhi/__init__.py
TamilSandhi/helpers.py
TamilSandhi/rules/__init__.py
TamilSandhi/rules/vallinam_addition.py
TamilSandhi/rules/vallinam_deletion.py
tamilsandhi_toolkit-0.1.0.dist-info/METADATA
tamilsandhi_toolkit-0.1.0.dist-info/WHEEL
tamilsandhi_toolkit-0.1.0.dist-info/top_level.txt
tamilsandhi_toolkit-0.1.0.dist-info/RECORD
