Metadata-Version: 2.4
Name: tamilsandhi-toolkit
Version: 0.1.0
Summary: A Python library to detect and correct Tamil Sandhi errors using rule-based methods.
Home-page: https://github.com/TamilGeekGirl/TamilSandhiNeuroSymbolicAI/
Author: Yazhmozhi VM, Annalu Waller and Jacky Visser
Author-email: yazh.connect@gmail.com
License: MIT
Classifier: Programming Language :: Python :: 3
Classifier: License :: OSI Approved :: MIT License
Classifier: Natural Language :: Tamil
Classifier: Operating System :: OS Independent
Classifier: Topic :: Text Processing :: Linguistic
Requires-Python: >=3.6
Requires-Dist: open-tamil
Requires-Dist: pytest
Dynamic: author
Dynamic: author-email
Dynamic: classifier
Dynamic: description
Dynamic: description-content-type
Dynamic: home-page
Dynamic: license
Dynamic: requires-dist
Dynamic: requires-python
Dynamic: summary
